juice_simphony/CompositionEngine/Scenario/__init__.py
juice_simphony/CompositionEngine/Scenario/attitude/__init__.py
juice_simphony/CompositionEngine/Scenario/attitude/attitude.py
juice_simphony/CompositionEngine/Scenario/attitude/xml_attitude.py
juice_simphony/CompositionEngine/Scenario/common/__init__.py
juice_simphony/CompositionEngine/Scenario/common/fileHandle.py
juice_simphony/CompositionEngine/Scenario/common/fileHandleEps.py
juice_simphony/CompositionEngine/Scenario/common/fileHandleEps1.py
juice_simphony/CompositionEngine/Scenario/common/fileHandleTml.py
juice_simphony/CompositionEngine/Scenario/common/fileHandleXML.py
juice_simphony/CompositionEngine/Scenario/common/fileName.py
juice_simphony/CompositionEngine/Scenario/common/fileTemplate.py
juice_simphony/CompositionEngine/Scenario/common/utils.py
juice_simphony/CompositionEngine/Scenario/config/__init__.py
juice_simphony/CompositionEngine/Scenario/config/agmCfgFiles.py
juice_simphony/CompositionEngine/Scenario/config/agmIniFile.py
juice_simphony/CompositionEngine/Scenario/config/configuration.py
juice_simphony/CompositionEngine/Scenario/config/epsEvtDefFile.py
juice_simphony/CompositionEngine/Scenario/config/epsFile.py
juice_simphony/CompositionEngine/Scenario/config/mappsIniFile.py
juice_simphony/CompositionEngine/Scenario/config/notebooks.py
juice_simphony/CompositionEngine/Scenario/definitions/__init__.py
juice_simphony/CompositionEngine/Scenario/definitions/definitions.py
juice_simphony/CompositionEngine/Scenario/definitions/toplevelObsDef.py
juice_simphony/CompositionEngine/Scenario/environment/__init__.py
juice_simphony/CompositionEngine/Scenario/environment/environment.py
juice_simphony/CompositionEngine/Scenario/environment/trajectory.py
juice_simphony/CompositionEngine/Scenario/graphicalPath.py
juice_simphony/CompositionEngine/Scenario/main.py
juice_simphony/CompositionEngine/Scenario/modelling/__init__.py
juice_simphony/CompositionEngine/Scenario/modelling/experiment/experiment.py
juice_simphony-0.1.3.dist-info/LICENSE.txt
juice_simphony-0.1.3.dist-info/METADATA
juice_simphony-0.1.3.dist-info/WHEEL
juice_simphony-0.1.3.dist-info/entry_points.txt
juice_simphony-0.1.3.dist-info/RECORD
