Metadata-Version: 2.1
Name: juice-simphony
Version: 0.1.3
Summary: JUICE Scenario Generator
License: ESA
Author: JUICE SOC Team
Requires-Python: >=3.10
Classifier: License :: Other/Proprietary License
Classifier: Programming Language :: Python :: 3
Classifier: Programming Language :: Python :: 3.10
Classifier: Programming Language :: Python :: 3.11
Classifier: Programming Language :: Python :: 3.12
Requires-Dist: jinja2 (>=3.1.6,<4.0.0)
Requires-Dist: python-dotenv (>=1.1.0,<2.0.0)
Requires-Dist: requests (>=2.32.3,<3.0.0)
Requires-Dist: setuptools (>=80.3.1,<81.0.0)
